LICENSE
README.md
pyproject.toml
requirements.txt
setup.cfg
setup.py
lavaMase/__init__.py
lavaMase/enums.py
lavaMase/exceptions.py
lavaMase/filters.py
lavaMase/lfu.py
lavaMase/node.py
lavaMase/payloads.py
lavaMase/player.py
lavaMase/py.typed
lavaMase/queue.py
lavaMase/tracks.py
lavaMase/websocket.py
lavaMase.egg-info/PKG-INFO
lavaMase.egg-info/SOURCES.txt
lavaMase.egg-info/dependency_links.txt
lavaMase.egg-info/not-zip-safe
lavaMase.egg-info/requires.txt
lavaMase.egg-info/top_level.txt
lavaMase/types/__init__.py
lavaMase/types/filters.py
lavaMase/types/request.py
lavaMase/types/response.py
lavaMase/types/state.py
lavaMase/types/stats.py
lavaMase/types/tracks.py
lavaMase/types/websocket.py
lavaMase/utils/__init__.py
lavaMase/utils/classproperty.py
lavaMase/utils/namespace.py
lavaMase/utils/decode/__init__.py
lavaMase/utils/decode/dotaio.py
lavaMase/utils/decode/utfm_codec.py